msgcenterpy/__init__.py
msgcenterpy/__pycache__/__init__.cpython-310.pyc
msgcenterpy/core/__init__.py
msgcenterpy/core/envelope.py
msgcenterpy/core/field_accessor.py
msgcenterpy/core/message_center.py
msgcenterpy/core/message_instance.py
msgcenterpy/core/type_converter.py
msgcenterpy/core/type_info.py
msgcenterpy/core/types.py
msgcenterpy/core/__pycache__/__init__.cpython-310.pyc
msgcenterpy/core/__pycache__/envelope.cpython-310.pyc
msgcenterpy/core/__pycache__/field_accessor.cpython-310.pyc
msgcenterpy/core/__pycache__/message_center.cpython-310.pyc
msgcenterpy/core/__pycache__/message_instance.cpython-310.pyc
msgcenterpy/core/__pycache__/type_converter.cpython-310.pyc
msgcenterpy/core/__pycache__/type_info.cpython-310.pyc
msgcenterpy/core/__pycache__/types.cpython-310.pyc
msgcenterpy/instances/__init__.py
msgcenterpy/instances/json_schema_instance.py
msgcenterpy/instances/ros2_instance.py
msgcenterpy/instances/__pycache__/__init__.cpython-310.pyc
msgcenterpy/instances/__pycache__/json_schema_instance.cpython-310.pyc
msgcenterpy/instances/__pycache__/ros2_instance.cpython-310.pyc
msgcenterpy/utils/__init__.py
msgcenterpy/utils/decorator.py
msgcenterpy/utils/__pycache__/__init__.cpython-310.pyc
msgcenterpy/utils/__pycache__/decorator.cpython-310.pyc
msgcenterpy-0.1.4.dist-info/licenses/LICENSE
msgcenterpy-0.1.4.dist-info/METADATA
msgcenterpy-0.1.4.dist-info/WHEEL
msgcenterpy-0.1.4.dist-info/top_level.txt
msgcenterpy-0.1.4.dist-info/RECORD
