Metadata-Version: 2.4
Name: msgcenterpy
Version: 0.1.4
Summary: Unified message conversion system supporting ROS2, Pydantic, Dataclass, JSON, YAML, Dict, and MCP schema inter-conversion
Author-email: MsgCenterPy Team <zgca@zgca.com>
License:                                  Apache License
Project-URL: Homepage, https://github.com/ZGCA-Forge/MsgCenterPy
Project-URL: Documentation, https://zgca-forge.github.io/MsgCenterPy/
Project-URL: Repository, https://github.com/ZGCA-Forge/MsgCenterPy
Project-URL: Issues, https://github.com/ZGCA-Forge/MsgCenterPy/issues
Keywords: message,conversion,ros2,pydantic,dataclass,json,yaml,mcp
Classifier: Development Status :: 3 - Alpha
Classifier: Intended Audience :: Developers
Classifier: Programming Language :: Python :: 3
Classifier: Programming Language :: Python :: 3.10
Classifier: Programming Language :: Python :: 3.11
Classifier: Programming Language :: Python :: 3.12
Classifier: Programming Language :: Python :: 3.13
Classifier: Topic :: Software Development :: Libraries :: Python Modules
Classifier: Topic :: System :: Distributed Computing
Classifier: Topic :: Scientific/Engineering :: Interface Engine/Protocol Translator
Requires-Python: >=3.10
License-File: LICENSE
Requires-Dist: pydantic>=2.0.0
Requires-Dist: jsonschema>=4.25
Requires-Dist: PyYAML>=6.0
Requires-Dist: typing-extensions>=4.0.0; python_version < "3.11"
Provides-Extra: ros2
Requires-Dist: rosidl_runtime_py>=0.9.0; extra == "ros2"
Requires-Dist: rclpy>=3.0.0; extra == "ros2"
Provides-Extra: dev
Requires-Dist: pytest>=7.0.0; extra == "dev"
Requires-Dist: black>=22.0.0; extra == "dev"
Requires-Dist: isort>=5.0.0; extra == "dev"
Requires-Dist: mypy>=1.0.0; extra == "dev"
Requires-Dist: types-jsonschema>=4.0.0; extra == "dev"
Requires-Dist: types-PyYAML>=6.0.0; extra == "dev"
Requires-Dist: pre-commit>=2.20.0; extra == "dev"
Requires-Dist: bump2version>=1.0.0; extra == "dev"
Provides-Extra: docs
Requires-Dist: sphinx>=5.0.0; extra == "docs"
Requires-Dist: sphinx-rtd-theme>=1.0.0; extra == "docs"
Requires-Dist: myst-parser>=0.18.0; extra == "docs"
Provides-Extra: all
Requires-Dist: msgcenterpy[dev,docs,ros2]; extra == "all"
Dynamic: license-file
